django_storage_url/__init__.py
django_storage_url/base.py
django_storage_url/backends/__init__.py
django_storage_url/backends/az.py
django_storage_url/backends/file.py
django_storage_url/backends/not_implemented.py
django_storage_url/backends/s3.py
tests/__init__.py
tests/settings.py
tests/test_migrations.py
tests/test_s3.py
tests/test_serialization.py
django_storage_url-0.12.1.dist-info/LICENSE
django_storage_url-0.12.1.dist-info/METADATA
django_storage_url-0.12.1.dist-info/WHEEL
django_storage_url-0.12.1.dist-info/top_level.txt
django_storage_url-0.12.1.dist-info/RECORD
